{
  "victim_ip": "217.80.150.244",
  "victim_port": "80",
  "timestamp": "2021-12-28T08:08:43.541Z",
  "cnc_ip": "23.94.138.57",
  "cnc_port": 34241
}
{
  "victim_ip": "217.80.150.244",
  "victim_port": "80",
  "timestamp": "2021-12-28T08:08:46.953Z",
  "cnc_ip": "23.94.138.57",
  "cnc_port": 34241
}
{
  "victim_ip": "217.80.150.244",
  "victim_port": "80",
  "timestamp": "2021-12-28T08:08:47.673Z",
  "cnc_ip": "23.94.138.57",
  "cnc_port": 34241
}
{
  "victim_ip": "217.80.150.244",
  "victim_port": "80",
  "timestamp": "2021-12-28T08:08:49.198Z",
  "cnc_ip": "23.94.138.57",
  "cnc_port": 34241
}
